colorbykawa/__init__.py
colorlibx-5.0.0.dist-info/LICENSE
colorlibx-5.0.0.dist-info/METADATA
colorlibx-5.0.0.dist-info/WHEEL
colorlibx-5.0.0.dist-info/top_level.txt
colorlibx-5.0.0.dist-info/RECORD
