Metadata-Version: 2.1
Name: colorlibx
Version: 5.0.0
Summary: A library for adding color to terminal text with support for 50 predefined colors, 256-color palette, and custom HEX/RGB colors.
Author: kawa1
Author-email: kawa1337k@gmail.com
Keywords: color terminal text ANSI colors HEX RGB
Classifier: Programming Language :: Python :: 3
Classifier: License :: OSI Approved :: MIT License
Classifier: Operating System :: OS Independent
Classifier: Programming Language :: Python :: 3.6
Classifier: Programming Language :: Python :: 3.7
Classifier: Programming Language :: Python :: 3.8
Classifier: Programming Language :: Python :: 3.9
Classifier: Programming Language :: Python :: 3.10
Classifier: Programming Language :: Python :: 3.11
Requires-Python: >=3.6
License-File: LICENSE
